__init__.py
goechargerv2/__init__.py
goechargerv2/goecharger.py
goechargerv2/validations.py
smart_energy.goecharger_api-0.3.1.dist-info/LICENSE
smart_energy.goecharger_api-0.3.1.dist-info/METADATA
smart_energy.goecharger_api-0.3.1.dist-info/WHEEL
smart_energy.goecharger_api-0.3.1.dist-info/top_level.txt
smart_energy.goecharger_api-0.3.1.dist-info/RECORD
