Metadata-Version: 2.1
Name: smart-energy.goecharger-api
Version: 0.3.1
Summary: API library for the go-eCharger.
Author-email: Ingmar Mueller <ingmar.mueller@kfw.de>, Mario Macai <mario.macai@accenture.com>
Project-URL: Bug Tracker, https://github.com/openkfw/smartenergy.goecharger-api/issues
Project-URL: Homepage, https://github.com/openkfw/smartenergy.goecharger-api
Keywords: goecharger,kfw,api,cloud
Classifier: Programming Language :: Python :: 3
Classifier: License :: OSI Approved :: GNU General Public License v3 (GPLv3)
Classifier: Operating System :: OS Independent
Requires-Python: >=3.7
License-File: LICENSE
Requires-Dist: requests (>=2.27.1)
Provides-Extra: dev
Requires-Dist: black ; extra == 'dev'
Requires-Dist: pylint ; extra == 'dev'
Requires-Dist: python-dotenv ; extra == 'dev'
Requires-Dist: pytest ; extra == 'dev'
Requires-Dist: pre-commit ; extra == 'dev'
